README.md
setup.py
TOPSIS_Kartikey/__init__.py
TOPSIS_Kartikey/topsis_kartikey.py
TOPSIS_kartikey_101803606.egg-info/PKG-INFO
TOPSIS_kartikey_101803606.egg-info/SOURCES.txt
TOPSIS_kartikey_101803606.egg-info/dependency_links.txt
TOPSIS_kartikey_101803606.egg-info/requires.txt
TOPSIS_kartikey_101803606.egg-info/top_level.txt