Metadata-Version: 2.1
Name: TOPSIS-kartikey-101803606
Version: 1.0.0
Summary: TOPSIS Score Calculator
Home-page: UNKNOWN
Author: Kartikey Nigam
Author-email: knigam_be18@thapar.edu
License: MIT
Keywords: TOPSIS
Platform: UNKNOWN
Classifier: Development Status :: 3 - Alpha
Classifier: Intended Audience :: Developers
Classifier: Topic :: Software Development :: Build Tools
Classifier: License :: OSI Approved :: MIT License
Classifier: Programming Language :: Python :: 3
Classifier: Programming Language :: Python :: 3.4
Classifier: Programming Language :: Python :: 3.5
Classifier: Programming Language :: Python :: 3.6
